decouple_multi.py
python_decouple_multi-0.1.1.dist-info/METADATA
python_decouple_multi-0.1.1.dist-info/WHEEL
python_decouple_multi-0.1.1.dist-info/historia.json
python_decouple_multi-0.1.1.dist-info/top_level.txt
python_decouple_multi-0.1.1.dist-info/RECORD
